Metadata-Version: 2.4
Name: time-server-pkg
Version: 0.1.0
Summary: 提供JSON-RPC接口的时间服务器，支持获取不同时区的当前时间
Home-page: https://github.com/yourusername/time-server-pkg
Author: Your Name
Author-email: Your Name <your.email@example.com>
License: MIT License
Keywords: time-server,json-rpc,fastapi,timezone
Classifier: Programming Language :: Python :: 3
Classifier: License :: OSI Approved :: MIT License
Classifier: Operating System :: OS Independent
Classifier: Framework :: FastAPI
Requires-Python: >=3.7
License-File: LICENSE
Requires-Dist: fastapi>=0.100.0
Requires-Dist: uvicorn>=0.22.0
Requires-Dist: pytz>=2023.3
Dynamic: author
Dynamic: home-page
Dynamic: license-file
Dynamic: requires-python
